LICENSE
MANIFEST.in
README.md
VERSION
requirements.txt
setup.py
bin/add_meta
bin/gwrucio_checksums
bin/gwrucio_fileinfo_pipe
bin/gwrucio_registrar
bin/gwrucio_registrar_1g
bin/gwrucio_update_dataset
bin/meta_daemon
lib/gwrucio/__init__.py
lib/gwrucio/register.py
lib/gwrucio/registrar.py
lib/gwrucio/utils.py
lib/gwrucio_registrar.egg-info/PKG-INFO
lib/gwrucio_registrar.egg-info/SOURCES.txt
lib/gwrucio_registrar.egg-info/dependency_links.txt
lib/gwrucio_registrar.egg-info/requires.txt
lib/gwrucio_registrar.egg-info/top_level.txt
lib/ldr/__init__.py
lib/ldr/diskcache.py