Metadata-Version: 2.1
Name: gwrucio-registrar
Version: 1.0.2
Summary: Client utils for IGWN
Home-page: https://git.ligo.org/rucio/igwn-rucio-client
Author: James Alexander Clark
Author-email: james.clark@ligo.org
License: UNKNOWN
Platform: UNKNOWN
Classifier: Programming Language :: Python :: 2
Classifier: Programming Language :: Python :: 3
Classifier: License :: OSI Approved :: GNU General Public License v3 (GPLv3)
Classifier: Operating System :: OS Independent
